[{"gameId": "0041900406", "teamA": "Miami Heat", "teamB": "Los Angeles Lakers", "date": "2020-10-11", "finalScoreA": 93, "finalScoreB": 106}, {"gameId": "0041900405", "teamA": "Los Angeles Lakers", "teamB": "Miami Heat", "date": "2020-10-09", "finalScoreA": 108, "finalScoreB": 111}, {"gameId": "0041900404", "teamA": "Miami Heat", "teamB": "Los Angeles Lakers", "date": "2020-10-06", "finalScoreA": 96, "finalScoreB": 102}, {"gameId": "0041900403", "teamA": "Miami Heat", "teamB": "Los Angeles Lakers", "date": "2020-10-04", "finalScoreA": 115, "finalScoreB": 104}, {"gameId": "0041900402", "teamA": "Los Angeles Lakers", "teamB": "Miami Heat", "date": "2020-10-02", "finalScoreA": 124, "finalScoreB": 114}, {"gameId": "0041900401", "teamA": "Los Angeles Lakers", "teamB": "Miami Heat", "date": "2020-09-30", "finalScoreA": 116, "finalScoreB": 98}, {"gameId": "0041900306", "teamA": "Miami Heat", "teamB": "Boston Celtics", "date": "2020-09-27", "finalScoreA": 125, "finalScoreB": 113}, {"gameId": "0041900315", "teamA": "Los Angeles Lakers", "teamB": "Denver Nuggets", "date": "2020-09-26", "finalScoreA": 117, "finalScoreB": 107}, {"gameId": "0041900305", "teamA": "Boston Celtics", "teamB": "Miami Heat", "date": "2020-09-25", "finalScoreA": 121, "finalScoreB": 108}, {"gameId": "0041900314", "teamA": "Denver Nuggets", "teamB": "Los Angeles Lakers", "date": "2020-09-24", "finalScoreA": 108, "finalScoreB": 114}, {"gameId": "0041900304", "teamA": "Miami Heat", "teamB": "Boston Celtics", "date": "2020-09-23", "finalScoreA": 112, "finalScoreB": 109}, {"gameId": "0041900313", "teamA": "Denver Nuggets", "teamB": "Los Angeles Lakers", "date": "2020-09-22", "finalScoreA": 114, "finalScoreB": 106}, {"gameId": "0041900312", "teamA": "Los Angeles Lakers", "teamB": "Denver Nuggets", "date": "2020-09-20", "finalScoreA": 105, "finalScoreB": 103}, {"gameId": "0041900303", "teamA": "Miami Heat", "teamB": "Boston Celtics", "date": "2020-09-19", "finalScoreA": 106, "finalScoreB": 117}, {"gameId": "0041900311", "teamA": "Los Angeles Lakers", "teamB": "Denver Nuggets", "date": "2020-09-18", "finalScoreA": 126, "finalScoreB": 114}, {"gameId": "0041900302", "teamA": "Boston Celtics", "teamB": "Miami Heat", "date": "2020-09-17", "finalScoreA": 101, "finalScoreB": 106}, {"gameId": "0041900301", "teamA": "Boston Celtics", "teamB": "Miami Heat", "date": "2020-09-15", "finalScoreA": 114, "finalScoreB": 117}, {"gameId": "0041900237", "teamA": "LA Clippers", "teamB": "Denver Nuggets", "date": "2020-09-15", "finalScoreA": 89, "finalScoreB": 104}, {"gameId": "0041900236", "teamA": "Denver Nuggets", "teamB": "LA Clippers", "date": "2020-09-13", "finalScoreA": 111, "finalScoreB": 98}, {"gameId": "0041900225", "teamA": "Los Angeles Lakers", "teamB": "Houston Rockets", "date": "2020-09-12", "finalScoreA": 119, "finalScoreB": 96}, {"gameId": "0041900235", "teamA": "LA Clippers", "teamB": "Denver Nuggets", "date": "2020-09-11", "finalScoreA": 105, "finalScoreB": 111}, {"gameId": "0041900217", "teamA": "Toronto Raptors", "teamB": "Boston Celtics", "date": "2020-09-11", "finalScoreA": 87, "finalScoreB": 92}, {"gameId": "0041900224", "teamA": "Houston Rockets", "teamB": "Los Angeles Lakers", "date": "2020-09-10", "finalScoreA": 100, "finalScoreB": 110}, {"gameId": "0041900216", "teamA": "Boston Celtics", "teamB": "Toronto Raptors", "date": "2020-09-09", "finalScoreA": 122, "finalScoreB": 125}, {"gameId": "0041900234", "teamA": "Denver Nuggets", "teamB": "LA Clippers", "date": "2020-09-09", "finalScoreA": 85, "finalScoreB": 96}, {"gameId": "0041900205", "teamA": "Milwaukee Bucks", "teamB": "Miami Heat", "date": "2020-09-08", "finalScoreA": 94, "finalScoreB": 103}, {"gameId": "0041900223", "teamA": "Houston Rockets", "teamB": "Los Angeles Lakers", "date": "2020-09-08", "finalScoreA": 102, "finalScoreB": 112}, {"gameId": "0041900215", "teamA": "Toronto Raptors", "teamB": "Boston Celtics", "date": "2020-09-07", "finalScoreA": 89, "finalScoreB": 111}, {"gameId": "0041900233", "teamA": "Denver Nuggets", "teamB": "LA Clippers", "date": "2020-09-07", "finalScoreA": 107, "finalScoreB": 113}, {"gameId": "0041900204", "teamA": "Miami Heat", "teamB": "Milwaukee Bucks", "date": "2020-09-06", "finalScoreA": 115, "finalScoreB": 118}, {"gameId": "0041900222", "teamA": "Los Angeles Lakers", "teamB": "Houston Rockets", "date": "2020-09-06", "finalScoreA": 117, "finalScoreB": 109}, {"gameId": "0041900214", "teamA": "Boston Celtics", "teamB": "Toronto Raptors", "date": "2020-09-05", "finalScoreA": 93, "finalScoreB": 100}, {"gameId": "0041900232", "teamA": "LA Clippers", "teamB": "Denver Nuggets", "date": "2020-09-05", "finalScoreA": 101, "finalScoreB": 110}, {"gameId": "0041900203", "teamA": "Miami Heat", "teamB": "Milwaukee Bucks", "date": "2020-09-04", "finalScoreA": 115, "finalScoreB": 100}, {"gameId": "0041900221", "teamA": "Los Angeles Lakers", "teamB": "Houston Rockets", "date": "2020-09-04", "finalScoreA": 97, "finalScoreB": 112}, {"gameId": "0041900213", "teamA": "Boston Celtics", "teamB": "Toronto Raptors", "date": "2020-09-03", "finalScoreA": 103, "finalScoreB": 104}, {"gameId": "0041900231", "teamA": "LA Clippers", "teamB": "Denver Nuggets", "date": "2020-09-03", "finalScoreA": 120, "finalScoreB": 97}, {"gameId": "0041900202", "teamA": "Milwaukee Bucks", "teamB": "Miami Heat", "date": "2020-09-02", "finalScoreA": 114, "finalScoreB": 116}, {"gameId": "0041900177", "teamA": "Houston Rockets", "teamB": "Oklahoma City Thunder", "date": "2020-09-02", "finalScoreA": 104, "finalScoreB": 102}, {"gameId": "0041900212", "teamA": "Toronto Raptors", "teamB": "Boston Celtics", "date": "2020-09-01", "finalScoreA": 99, "finalScoreB": 102}, {"gameId": "0041900167", "teamA": "Denver Nuggets", "teamB": "Utah Jazz", "date": "2020-09-01", "finalScoreA": 80, "finalScoreB": 78}, {"gameId": "0041900201", "teamA": "Milwaukee Bucks", "teamB": "Miami Heat", "date": "2020-08-31", "finalScoreA": 104, "finalScoreB": 115}, {"gameId": "0041900176", "teamA": "Oklahoma City Thunder", "teamB": "Houston Rockets", "date": "2020-08-31", "finalScoreA": 104, "finalScoreB": 100}, {"gameId": "0041900211", "teamA": "Toronto Raptors", "teamB": "Boston Celtics", "date": "2020-08-30", "finalScoreA": 94, "finalScoreB": 112}, {"gameId": "0041900156", "teamA": "Dallas Mavericks", "teamB": "LA Clippers", "date": "2020-08-30", "finalScoreA": 97, "finalScoreB": 111}, {"gameId": "0041900166", "teamA": "Utah Jazz", "teamB": "Denver Nuggets", "date": "2020-08-30", "finalScoreA": 107, "finalScoreB": 119}, {"gameId": "0041900105", "teamA": "Milwaukee Bucks", "teamB": "Orlando Magic", "date": "2020-08-29", "finalScoreA": 118, "finalScoreB": 104}, {"gameId": "0041900175", "teamA": "Houston Rockets", "teamB": "Oklahoma City Thunder", "date": "2020-08-29", "finalScoreA": 114, "finalScoreB": 80}, {"gameId": "0041900145", "teamA": "Los Angeles Lakers", "teamB": "Portland Trail Blazers", "date": "2020-08-29", "finalScoreA": 131, "finalScoreB": 122}, {"gameId": "0041900165", "teamA": "Denver Nuggets", "teamB": "Utah Jazz", "date": "2020-08-25", "finalScoreA": 117, "finalScoreB": 107}, {"gameId": "0041900155", "teamA": "LA Clippers", "teamB": "Dallas Mavericks", "date": "2020-08-25", "finalScoreA": 154, "finalScoreB": 111}, {"gameId": "0041900104", "teamA": "Orlando Magic", "teamB": "Milwaukee Bucks", "date": "2020-08-24", "finalScoreA": 106, "finalScoreB": 121}, {"gameId": "0041900174", "teamA": "Oklahoma City Thunder", "teamB": "Houston Rockets", "date": "2020-08-24", "finalScoreA": 117, "finalScoreB": 114}, {"gameId": "0041900134", "teamA": "Miami Heat", "teamB": "Indiana Pacers", "date": "2020-08-24", "finalScoreA": 99, "finalScoreB": 87}, {"gameId": "0041900144", "teamA": "Portland Trail Blazers", "teamB": "Los Angeles Lakers", "date": "2020-08-24", "finalScoreA": 115, "finalScoreB": 135}, {"gameId": "0041900124", "teamA": "Philadelphia 76ers", "teamB": "Boston Celtics", "date": "2020-08-23", "finalScoreA": 106, "finalScoreB": 110}, {"gameId": "0041900154", "teamA": "Dallas Mavericks", "teamB": "LA Clippers", "date": "2020-08-23", "finalScoreA": 135, "finalScoreB": 133}, {"gameId": "0041900114", "teamA": "Brooklyn Nets", "teamB": "Toronto Raptors", "date": "2020-08-23", "finalScoreA": 122, "finalScoreB": 150}, {"gameId": "0041900164", "teamA": "Utah Jazz", "teamB": "Denver Nuggets", "date": "2020-08-23", "finalScoreA": 129, "finalScoreB": 127}, {"gameId": "0041900103", "teamA": "Orlando Magic", "teamB": "Milwaukee Bucks", "date": "2020-08-22", "finalScoreA": 107, "finalScoreB": 121}, {"gameId": "0041900133", "teamA": "Miami Heat", "teamB": "Indiana Pacers", "date": "2020-08-22", "finalScoreA": 124, "finalScoreB": 115}, {"gameId": "0041900173", "teamA": "Oklahoma City Thunder", "teamB": "Houston Rockets", "date": "2020-08-22", "finalScoreA": 119, "finalScoreB": 107}, {"gameId": "0041900143", "teamA": "Portland Trail Blazers", "teamB": "Los Angeles Lakers", "date": "2020-08-22", "finalScoreA": 108, "finalScoreB": 116}, {"gameId": "0041900113", "teamA": "Brooklyn Nets", "teamB": "Toronto Raptors", "date": "2020-08-21", "finalScoreA": 92, "finalScoreB": 117}, {"gameId": "0041900163", "teamA": "Utah Jazz", "teamB": "Denver Nuggets", "date": "2020-08-21", "finalScoreA": 124, "finalScoreB": 87}, {"gameId": "0041900123", "teamA": "Philadelphia 76ers", "teamB": "Boston Celtics", "date": "2020-08-21", "finalScoreA": 94, "finalScoreB": 102}, {"gameId": "0041900153", "teamA": "Dallas Mavericks", "teamB": "LA Clippers", "date": "2020-08-21", "finalScoreA": 122, "finalScoreB": 130}, {"gameId": "0041900132", "teamA": "Indiana Pacers", "teamB": "Miami Heat", "date": "2020-08-20", "finalScoreA": 100, "finalScoreB": 109}, {"gameId": "0041900172", "teamA": "Houston Rockets", "teamB": "Oklahoma City Thunder", "date": "2020-08-20", "finalScoreA": 111, "finalScoreB": 98}, {"gameId": "0041900102", "teamA": "Milwaukee Bucks", "teamB": "Orlando Magic", "date": "2020-08-20", "finalScoreA": 111, "finalScoreB": 96}, {"gameId": "0041900142", "teamA": "Los Angeles Lakers", "teamB": "Portland Trail Blazers", "date": "2020-08-20", "finalScoreA": 111, "finalScoreB": 88}, {"gameId": "0041900112", "teamA": "Toronto Raptors", "teamB": "Brooklyn Nets", "date": "2020-08-19", "finalScoreA": 104, "finalScoreB": 99}, {"gameId": "0041900162", "teamA": "Denver Nuggets", "teamB": "Utah Jazz", "date": "2020-08-19", "finalScoreA": 105, "finalScoreB": 124}, {"gameId": "0041900122", "teamA": "Boston Celtics", "teamB": "Philadelphia 76ers", "date": "2020-08-19", "finalScoreA": 128, "finalScoreB": 101}, {"gameId": "0041900152", "teamA": "LA Clippers", "teamB": "Dallas Mavericks", "date": "2020-08-19", "finalScoreA": 114, "finalScoreB": 127}, {"gameId": "0041900101", "teamA": "Milwaukee Bucks", "teamB": "Orlando Magic", "date": "2020-08-18", "finalScoreA": 110, "finalScoreB": 122}, {"gameId": "0041900131", "teamA": "Indiana Pacers", "teamB": "Miami Heat", "date": "2020-08-18", "finalScoreA": 101, "finalScoreB": 113}, {"gameId": "0041900171", "teamA": "Houston Rockets", "teamB": "Oklahoma City Thunder", "date": "2020-08-18", "finalScoreA": 123, "finalScoreB": 108}, {"gameId": "0041900141", "teamA": "Los Angeles Lakers", "teamB": "Portland Trail Blazers", "date": "2020-08-18", "finalScoreA": 93, "finalScoreB": 100}, {"gameId": "0041900161", "teamA": "Denver Nuggets", "teamB": "Utah Jazz", "date": "2020-08-17", "finalScoreA": 135, "finalScoreB": 125}, {"gameId": "0041900111", "teamA": "Toronto Raptors", "teamB": "Brooklyn Nets", "date": "2020-08-17", "finalScoreA": 134, "finalScoreB": 110}, {"gameId": "0041900121", "teamA": "Boston Celtics", "teamB": "Philadelphia 76ers", "date": "2020-08-17", "finalScoreA": 109, "finalScoreB": 101}, {"gameId": "0041900151", "teamA": "LA Clippers", "teamB": "Dallas Mavericks", "date": "2020-08-17", "finalScoreA": 118, "finalScoreB": 110}]